dazvol/__init__.py
dazvol/authorization.py
dazvol-0.1.0.dist-info/LICENSE
dazvol-0.1.0.dist-info/WHEEL
dazvol-0.1.0.dist-info/METADATA
dazvol-0.1.0.dist-info/RECORD
